scisdk/__init__.py
scisdk/scisdk.py
scisdk/scisdk_defines.py
scisdk-1.4.dist-info/METADATA
scisdk-1.4.dist-info/WHEEL
scisdk-1.4.dist-info/licenses/LICENSE
scisdk-1.4.dist-info/RECORD
