Metadata-Version: 2.4
Name: scisdk
Version: 1.4
Summary: SDK for SciCompiler generated firmware
Project-URL: Homepage, https://github.com/NuclearInstruments/SCISDK
Project-URL: Bug Tracker, https://github.com/NuclearInstruments/SCISDK/issues
Author-email: Andrea Abba <abba@nuclearinstruments.eu>
License-File: LICENSE
Keywords: CAEN,Nuclear Instruments,SciCompiler,firmware,fpga
Classifier: License :: OSI Approved :: MIT License
Classifier: Operating System :: OS Independent
Classifier: Programming Language :: Python :: 3
Requires-Python: >=3.5
